carboniq/__init__.py
carboniq/emissions.py
carboniq/gpu_utils.py
carboniq/metrics.py
tests/__init__.py
tests/test_carboniq.py
CarbonIQ-0.1.5.dist-info/LICENSE
CarbonIQ-0.1.5.dist-info/METADATA
CarbonIQ-0.1.5.dist-info/WHEEL
CarbonIQ-0.1.5.dist-info/entry_points.txt
CarbonIQ-0.1.5.dist-info/top_level.txt
CarbonIQ-0.1.5.dist-info/RECORD
