Metadata-Version: 2.1
Name: CarbonIQ
Version: 0.1.5
Summary: A Python package that monitors and tracks the carbon emissions of scripts and applications. It provides insights into the environmental impact of code by analyzing resource usage such as CPU, memory, disk I/O, network, and GPU utilization.
Home-page: https://github.com/ashikrafi/CarbonIQ
Author: Md Ashikur Rahman
Author-email: mdashikur.rafi@gmail.com
Classifier: Programming Language :: Python :: 3
Classifier: License :: OSI Approved :: MIT License
Classifier: Operating System :: OS Independent
Requires-Python: >=3.6
License-File: LICENSE
Requires-Dist: pynvml
Requires-Dist: psutil
